GEARLM/__init__.py
GEARLM/Simulated/__init__.py
GEARLM/Simulated/cache_utils.py
GEARLM/Simulated/compress_config.py
GEARLM/Simulated/compress_function.py
GEARLM/Simulated/cpp_kernels.py
GEARLM/Simulated/h2o_llama_self_written.py
GEARLM/Simulated/modeling_llama_new.py
GEARLM/Simulated/modeling_mistral.py
GEARLM/Simulated/modeling_mixtral.py
GEARLM/Simulated/utils.py
GEARLM/TrueCompression/__init__.py
GEARLM/TrueCompression/models/TrueCompressFunction.py
GEARLM/TrueCompression/models/TrueCompressLlama.py
GEARLM/TrueCompression/models/__init__.py
GEARLM/TrueCompression/models/cache_utils.py
GEARLM/TrueCompression/models/compress_config.py
GEARLM/TrueCompression/models/compressed_cache_utils.py
GEARLM/TrueCompression/models/cpp_kernels.py
GEARLM/TrueCompression/models/streaming_cache_utils.py
GEARLM/TrueCompression/models/utils.py
GEARLM/TrueCompression/old_models/__init__.py
GEARLM/TrueCompression/old_models/modeling_llama_old.py
GEARLM/TrueCompression/old_models/CompressUtils/TrueCompressFunction.py
GEARLM/TrueCompression/old_models/CompressUtils/__init__.py
GEARLM/TrueCompression/old_models/CompressUtils/compress_class.py
GEARLM-0.0.6.dist-info/METADATA
GEARLM-0.0.6.dist-info/WHEEL
GEARLM-0.0.6.dist-info/top_level.txt
GEARLM-0.0.6.dist-info/RECORD
